dailyrotatingfilehandler.py
dailyrotatingfilehandler-0.0.5.dist-info/METADATA
dailyrotatingfilehandler-0.0.5.dist-info/RECORD
dailyrotatingfilehandler-0.0.5.dist-info/WHEEL
dailyrotatingfilehandler-0.0.5.dist-info/top_level.txt
